laneswap/__init__.py
laneswap/adapters/__init__.py
laneswap/adapters/base.py
laneswap/adapters/discord.py
laneswap/adapters/mongodb.py
laneswap/api/__init__.py
laneswap/api/app.py
laneswap/api/dependencies.py
laneswap/api/main.py
laneswap/api/server.py
laneswap/api/middleware/__init__.py
laneswap/api/middleware/error_handler.py
laneswap/api/routers/__init__.py
laneswap/api/routers/health_check.py
laneswap/api/routers/heartbeat.py
laneswap/api/routers/progress.py
laneswap/client/__init__.py
laneswap/client/async_client.py
laneswap/client/sync_client.py
laneswap/core/__init__.py
laneswap/core/config.py
laneswap/core/exceptions.py
laneswap/core/heartbeat.py
laneswap/core/progress.py
laneswap/core/types.py
laneswap/core/utils.py
laneswap/core/validator.py
laneswap/examples/__init__.py
laneswap/examples/config_example.py
laneswap/examples/discord_webhook_example.py
laneswap/examples/final_check.py
laneswap/examples/mock_api_server.py
laneswap/examples/progress_service.py
laneswap/examples/simple_progress.py
laneswap/examples/simple_service.py
laneswap/examples/start_monitor.py
laneswap/examples/sync_client_example.py
laneswap/examples/system_check.py
laneswap/examples/terminal_monitor_example.py
laneswap/examples/verify_installation.py
laneswap/examples/weather_app_example.py
laneswap/models/__init__.py
laneswap/models/error.py
laneswap/models/heartbeat.py
laneswap/models/progress.py
laneswap/terminal/__init__.py
laneswap/terminal/ascii_art.py
laneswap/terminal/colors.py
laneswap/terminal/monitor.py
laneswap-0.1.3.dist-info/LICENSE
laneswap-0.1.3.dist-info/METADATA
laneswap-0.1.3.dist-info/WHEEL
laneswap-0.1.3.dist-info/entry_points.txt
laneswap-0.1.3.dist-info/top_level.txt
laneswap-0.1.3.dist-info/RECORD
