Metadata-Version: 2.1
Name: laneswap
Version: 0.1.3
Summary: A heartbeat monitoring system for distributed services
Home-page: https://github.com/laneswap/laneswap
Author: LaneSwap Team
Author-email: LaneSwap Team <laneswap@example.com>
License: MIT
Project-URL: Homepage, https://github.com/laneswap/laneswap
Project-URL: Documentation, https://github.com/laneswap/laneswap#readme
Project-URL: Issues, https://github.com/laneswap/laneswap/issues
Classifier: Development Status :: 4 - Beta
Classifier: Intended Audience :: Developers
Classifier: License :: OSI Approved :: MIT License
Classifier: Programming Language :: Python :: 3
Classifier: Programming Language :: Python :: 3.8
Classifier: Programming Language :: Python :: 3.9
Classifier: Programming Language :: Python :: 3.10
Classifier: Programming Language :: Python :: 3.11
Classifier: Topic :: Software Development :: Libraries
Classifier: Topic :: System :: Monitoring
Requires-Python: >=3.8
License-File: LICENSE
Requires-Dist: fastapi>=0.95.0
Requires-Dist: uvicorn>=0.21.0
Requires-Dist: pydantic>=2.0.0
Requires-Dist: motor>=3.1.0
Requires-Dist: aiohttp>=3.8.0
Requires-Dist: tabulate>=0.9.0
Requires-Dist: python-dateutil>=2.8.2
Provides-Extra: dev
Requires-Dist: pytest>=7.0.0; extra == "dev"
Requires-Dist: pytest-asyncio>=0.20.0; extra == "dev"
Requires-Dist: black>=23.0.0; extra == "dev"
Requires-Dist: isort>=5.12.0; extra == "dev"
Requires-Dist: mypy>=1.0.0; extra == "dev"
